priceloop/__init__.py
priceloop/exceptions.py
priceloop/helpers.py
priceloop/table_utils.py
priceloop-0.1.0.dist-info/WHEEL
priceloop-0.1.0.dist-info/METADATA
priceloop-0.1.0.dist-info/RECORD
